Workbook

Sheet Inicio
A1: Método Embalse · Plantilla de cálculo
A2: Complemento del libro «Ingresos variables, sueldo fijo». Material educativo; no constituye asesoramiento financiero ni fiscal.
B4: Cómo se usa
B5: Celdas amarillas | C5: Son las que completas tú. Todo lo demás se calcula solo.
B6: Celdas celestes | C6: Resultados calculados. No hace falta tocarlas.
B8: Orden recomendado
B9: 1 Ingresos | C9: Tus cobros brutos de los últimos 12 meses y tus clientes (capítulo 2).
B10: 2 Gastos | C10: Tu inventario de gastos personales clasificado (capítulo 3).
B11: 3 Sistema | C11: Tu porcentaje de impuestos, gastos de la actividad y respuestas para la meta del embalse. Aquí está la ficha completa de tu sistema (capítulos 4 a 7).
B12: 6 Previsiones | C12: Tus gastos irregulares del año: calcula el aporte mensual y el capital semilla (capítulo 8).
B13: 7 Tarifa | C13: Tu tarifa mínima viable y tu tarifa objetivo (capítulo 11).
B14: 4 Cobros | C14: Uso semanal: registra cada cobro y la reserva de impuestos que le corresponde.
B15: 5 Embalse | C15: Uso mensual: el día de pago, anota el saldo del embalse y obtén el sueldo sugerido, la zona del semáforo y la cascada (capítulos 6, 7 y 9).
B16: 8 Cartera 90 días | C16: Uso mensual: lo que esperas cobrar en los próximos tres meses, ponderado (capítulo 11).
B18: Google Sheets | C18: Archivo > Importar > Subir este archivo. Las fórmulas son compatibles.
B19: Moneda | C19: Usa una sola moneda de referencia en toda la plantilla (capítulo 2).
B20: Aviso | C20: Los porcentajes de impuestos deben confirmarse con la autoridad tributaria de tu país o con un profesional. Los rangos de variabilidad y la tabla de meses del embalse son referencias propias del método.

Sheet 1 Ingresos
A1: 1 · Radiografía de tus ingresos
A2: Registra lo que efectivamente cobraste cada mes (criterio de caja), en bruto y en tu moneda de referencia.
A4: Mes | B4: Ingreso bruto | C4: Extraordinarios (no se cuentan) | D4: Impuestos estimados | E4: Gastos de la actividad | F4: Ingreso disponible | H4: Tus cinco números y tu variabilidad | I4: Valor
A5: Enero | D5: =IF(B5="","",B5*'3 Sistema'!$C$6) | E5: =IF(B5="","",'3 Sistema'!$C$8) | F5: =IF(B5="","",B5-D5-E5) | H5: Promedio bruto | I5: =IFERROR(AVERAGE(B5:B16),0)
A6: Febrero | D6: =IF(B6="","",B6*'3 Sistema'!$C$6) | E6: =IF(B6="","",'3 Sistema'!$C$8) | F6: =IF(B6="","",B6-D6-E6) | H6: Promedio disponible | I6: =IFERROR(AVERAGE(F5:F16),0)
A7: Marzo | D7: =IF(B7="","",B7*'3 Sistema'!$C$6) | E7: =IF(B7="","",'3 Sistema'!$C$8) | F7: =IF(B7="","",B7-D7-E7) | H7: Mediana disponible | I7: =IFERROR(MEDIAN(F5:F16),0)
A8: Abril | D8: =IF(B8="","",B8*'3 Sistema'!$C$6) | E8: =IF(B8="","",'3 Sistema'!$C$8) | F8: =IF(B8="","",B8-D8-E8) | H8: Mínimo disponible | I8: =IFERROR(MIN(F5:F16),0)
A9: Mayo | D9: =IF(B9="","",B9*'3 Sistema'!$C$6) | E9: =IF(B9="","",'3 Sistema'!$C$8) | F9: =IF(B9="","",B9-D9-E9) | H9: Piso (promedio de los 3 peores meses) | I9: =IFERROR(AVERAGE(SMALL(F5:F16,1),SMALL(F5:F16,2),SMALL(F5:F16,3)),0)
A10: Junio | D10: =IF(B10="","",B10*'3 Sistema'!$C$6) | E10: =IF(B10="","",'3 Sistema'!$C$8) | F10: =IF(B10="","",B10-D10-E10) | H10: Máximo disponible | I10: =IFERROR(MAX(F5:F16),0)
A11: Julio | D11: =IF(B11="","",B11*'3 Sistema'!$C$6) | E11: =IF(B11="","",'3 Sistema'!$C$8) | F11: =IF(B11="","",B11-D11-E11) | H11: Desvío estándar del ingreso bruto | I11: =IFERROR(STDEVP(B5:B16),0)
A12: Agosto | D12: =IF(B12="","",B12*'3 Sistema'!$C$6) | E12: =IF(B12="","",'3 Sistema'!$C$8) | F12: =IF(B12="","",B12-D12-E12) | H12: Coeficiente de variación (CV) | I12: =IFERROR(I11/I5,0)
A13: Septiembre | D13: =IF(B13="","",B13*'3 Sistema'!$C$6) | E13: =IF(B13="","",'3 Sistema'!$C$8) | F13: =IF(B13="","",B13-D13-E13) | H13: Variabilidad | I13: =IF(COUNT(B5:B16)=0,"",IF(I12<0.15,"Baja",IF(I12<0.3,"Moderada",IF(I12<0.5,"Alta","Muy alta"))))
A14: Octubre | D14: =IF(B14="","",B14*'3 Sistema'!$C$6) | E14: =IF(B14="","",'3 Sistema'!$C$8) | F14: =IF(B14="","",B14-D14-E14) | H14: Atajo: piso bruto ÷ promedio bruto | I14: =IFERROR(AVERAGE(SMALL(B5:B16,1),SMALL(B5:B16,2),SMALL(B5:B16,3))/I5,0)
A15: Noviembre | D15: =IF(B15="","",B15*'3 Sistema'!$C$6) | E15: =IF(B15="","",'3 Sistema'!$C$8) | F15: =IF(B15="","",B15-D15-E15) | H15: Meses por debajo del promedio disponible | I15: =COUNTIF(F5:F16,"<"&I6)
A16: Diciembre | D16: =IF(B16="","",B16*'3 Sistema'!$C$6) | E16: =IF(B16="","",'3 Sistema'!$C$8) | F16: =IF(B16="","",B16-D16-E16) | H16: Meses con datos | I16: =COUNT(B5:B16)
A17: Total | B17: =SUM(B5:B16) | C17: =SUM(C5:C16) | D17: =SUM(D5:D16) | E17: =SUM(E5:E16) | F17: =SUM(F5:F16)
A18: La columna E toma por defecto tus gastos mensuales de la actividad (hoja 3). Puedes escribir encima el valor real de cada mes.
A21: Concentración de clientes (últimos 12 meses)
A22: Cliente | B22: Cobrado en el año | C22: % del total | H22: Cliente principal (% del total) | I22: =IFERROR(MAX(B23:B32)/SUM(B23:B32),0)
C23: =IF(B23="","",B23/SUM($B$23:$B$32)) | H23: Tres clientes principales (% del total) | I23: =IFERROR((LARGE(B23:B32,1)+IFERROR(LARGE(B23:B32,2),0)+IFERROR(LARGE(B23:B32,3),0))/SUM(B23:B32),0)
C24: =IF(B24="","",B24/SUM($B$23:$B$32)) | H24: Señal de alerta | I24: =IF(I22>0.4,"Un cliente supera el 40 %",IF(I23>0.8,"3 clientes superan el 80 %","Sin alerta"))
C25: =IF(B25="","",B25/SUM($B$23:$B$32))
C26: =IF(B26="","",B26/SUM($B$23:$B$32))
C27: =IF(B27="","",B27/SUM($B$23:$B$32))
C28: =IF(B28="","",B28/SUM($B$23:$B$32))
C29: =IF(B29="","",B29/SUM($B$23:$B$32))
C30: =IF(B30="","",B30/SUM($B$23:$B$32))
C31: =IF(B31="","",B31/SUM($B$23:$B$32))
C32: =IF(B32="","",B32/SUM($B$23:$B$32))

Sheet 2 Gastos
A1: 2 · Radiografía de tus gastos
A2: Gastos personales mensuales. Los gastos de tu actividad NO van aquí (van en la hoja 3).
A4: Gasto | B4: Categoría | C4: Monto mensual | D4: ¿Compromiso fijo? | E4: Nota | G4: Resumen | H4: Monto
A5: Gastos irregulares del año (desde la hoja 6) | B5: Previsión | C5: ='6 Previsiones'!$C$5 | D5: No | E5: Se calcula en la hoja 6. No la borres. | G5: Esenciales | H5: =SUMIF(B5:B44,"Esencial",C5:C44)
G6: Importantes | H6: =SUMIF(B5:B44,"Importante",C5:C44)
G7: Flexibles | H7: =SUMIF(B5:B44,"Flexible",C5:C44)
G8: Previsiones (mensual) | H8: =SUMIF(B5:B44,"Previsión",C5:C44)
G10: Costo de vida normal | H10: =H5+H6+H7+H8
G11: Modo ajuste (sin flexibles) | H11: =H5+H6+H8
G12: Número de supervivencia | H12: =H5
G14: Compromisos fijos | H14: =SUMIF(D5:D44,"Sí",C5:C44)
G15: Tu piso (hoja 1) | H15: ='1 Ingresos'!I9
G16: Regla del piso | H16: =IF(OR(H14=0,H15=0),"",IF(H14<=H15,"Cumple","No cumple: revisa compromisos fijos"))

Sheet 3 Sistema
A1: 3 · La ficha de tu sistema
A2: Completa las celdas amarillas. El resto se calcula a partir de las hojas 1, 2, 6 y 7.
B4: Reglas de entrada
B5: Moneda de referencia | D5: Por ejemplo: USD, EUR, MXN.
B6: % de reserva de impuestos (de cada cobro bruto) | D6: Capítulo 5. Si cobras IVA, además separas el 100 % del IVA (hoja 4).
B7: Día de barrido / día de pago | D7: Por ejemplo: viernes / día 1.
B8: Gastos de la actividad por mes | D8: Software, equipos (prorrateados), contador, comisiones… (capítulo 10).
B9: Colchón operativo de la cuenta de Entrada | C9: =C8 | D9: Un mes de gastos de la actividad.
B11: Sueldos
B12: Costo de vida normal | C12: ='2 Gastos'!H10
B13: Sueldo meta calculado (redondeado a la centena) | C13: =ROUNDUP(C12,-2)
B14: Sueldo meta ajustado a mano (opcional) | D14: Déjalo vacío para usar el calculado.
B15: SUELDO META | C15: =IF(C14="",C13,C14)
B16: Ingreso disponible promedio | C16: ='1 Ingresos'!I6
B17: 80 % del ingreso disponible promedio | C17: =0.8*C16
B18: Prueba del 80 % | C18: =IF(OR(C15=0,C16=0),"",IF(C15<=C17,"Cumple","No cumple: ver capítulo 6"))
B19: Número de supervivencia | C19: ='2 Gastos'!H12
B20: Sueldo en modo ajuste | C20: ='2 Gastos'!H11
B21: Piso | C21: ='1 Ingresos'!I9
B22: SUELDO DE ARRANQUE | C22: =MIN(C15,ROUNDUP(MAX(C19,C21),-2)) | D22: El mayor entre supervivencia y piso, redondeado, sin superar el sueldo meta.
B23: Umbral de transición (embalse antes de pagarte) | C23: =2*C15 | D23: Pasas al sueldo meta cuando el embalse alcanza este monto el día de pago.
B25: Meta del embalse
B26: Variabilidad (hoja 1) | C26: ='1 Ingresos'!I13
B27: Meses base | C27: =IF(C26="","",IF(C26="Baja",3,IF(C26="Moderada",4,IF(C26="Alta",6,9))))
B28: ¿Un cliente aporta más del 40 %? (+2) | C28: =IF('1 Ingresos'!I22>0.4,"Sí","No") | D28: Se calcula con la hoja 1.
B29: ¿Personas a cargo o eres el único ingreso del hogar? (+2)
B30: ¿Temporada baja con meses cercanos a cero? (+1)
B31: ¿Otro ingreso estable en el hogar cubre los esenciales? (−1)
B32: M (meses de sueldo meta, entre 3 y 12) | C32: =IF(C27="","",MAX(3,MIN(12,C27+IF(C28="Sí",2,0)+IF(C29="Sí",2,0)+IF(C30="Sí",1,0)-IF(C31="Sí",1,0))))
B33: META DEL EMBALSE | C33: =IF(C32="","",C32*C15)
B35: Semáforo (sueldos meta en el embalse después de pagarte)
B36: Verde: desde | C36: =3*C15 | D36: 3 sueldos meta o más: funcionamiento normal.
B37: Amarillo: desde | C37: =1*C15 | D37: Entre 1 y 3: sin compromisos fijos nuevos.
B38: Naranja: desde | C38: =0.5*C15 | D38: Entre medio y 1: modo ajuste y plan comercial.
B39: Rojo: por debajo de | C39: =0.5*C15 | D39: Modo supervivencia y protocolo rojo.
B41: Previsiones y tarifa
B42: Aporte mensual a previsiones | C42: ='6 Previsiones'!C5
B43: Capital semilla del primer año | C43: ='6 Previsiones'!C6
B44: Tarifa mínima viable (por hora) | C44: ='7 Tarifa'!C17
B45: Tarifa objetivo (por hora) | C45: ='7 Tarifa'!C18

Sheet 4 Cobros
A1: 4 · Registro de cobros
A2: Una línea por cobro. Úsala en tu ritual semanal (capítulo 14).
A4: Fecha | B4: Cliente | C4: Ingreso bruto (sin IVA) | D4: IVA cobrado | E4: % de reserva | F4: A Impuestos | G4: Queda en Entrada | H4: Mes (AAAAMM) | I4: ¿Barrido hecho? | K4: Totales del registro | L4: Monto
E5: =IF(C5="","",'3 Sistema'!$C$6) | F5: =IF(C5="","",C5*E5+N(D5)) | G5: =IF(C5="","",C5+N(D5)-F5) | H5: =IF(A5="","",YEAR(A5)*100+MONTH(A5)) | K5: Ingreso bruto registrado | L5: =SUM(C5:C304)
E6: =IF(C6="","",'3 Sistema'!$C$6) | F6: =IF(C6="","",C6*E6+N(D6)) | G6: =IF(C6="","",C6+N(D6)-F6) | H6: =IF(A6="","",YEAR(A6)*100+MONTH(A6)) | K6: Enviado a Impuestos | L6: =SUM(F5:F304)
E7: =IF(C7="","",'3 Sistema'!$C$6) | F7: =IF(C7="","",C7*E7+N(D7)) | G7: =IF(C7="","",C7+N(D7)-F7) | H7: =IF(A7="","",YEAR(A7)*100+MONTH(A7)) | K7: Cobros sin barrido marcado | L7: =COUNTIFS(C5:C304,"<>",I5:I304,"<>Sí")
E8: =IF(C8="","",'3 Sistema'!$C$6) | F8: =IF(C8="","",C8*E8+N(D8)) | G8: =IF(C8="","",C8+N(D8)-F8) | H8: =IF(A8="","",YEAR(A8)*100+MONTH(A8))
E9: =IF(C9="","",'3 Sistema'!$C$6) | F9: =IF(C9="","",C9*E9+N(D9)) | G9: =IF(C9="","",C9+N(D9)-F9) | H9: =IF(A9="","",YEAR(A9)*100+MONTH(A9)) | K9: Bruto de un mes (escribe AAAAMM)
E10: =IF(C10="","",'3 Sistema'!$C$6) | F10: =IF(C10="","",C10*E10+N(D10)) | G10: =IF(C10="","",C10+N(D10)-F10) | H10: =IF(A10="","",YEAR(A10)*100+MONTH(A10)) | K10: Total bruto de ese mes | L10: =IF(L9="","",SUMIF(H5:H304,L9,C5:C304))
E11: =IF(C11="","",'3 Sistema'!$C$6) | F11: =IF(C11="","",C11*E11+N(D11)) | G11: =IF(C11="","",C11+N(D11)-F11) | H11: =IF(A11="","",YEAR(A11)*100+MONTH(A11))
E12: =IF(C12="","",'3 Sistema'!$C$6) | F12: =IF(C12="","",C12*E12+N(D12)) | G12: =IF(C12="","",C12+N(D12)-F12) | H12: =IF(A12="","",YEAR(A12)*100+MONTH(A12))
E13: =IF(C13="","",'3 Sistema'!$C$6) | F13: =IF(C13="","",C13*E13+N(D13)) | G13: =IF(C13="","",C13+N(D13)-F13) | H13: =IF(A13="","",YEAR(A13)*100+MONTH(A13))
E14: =IF(C14="","",'3 Sistema'!$C$6) | F14: =IF(C14="","",C14*E14+N(D14)) | G14: =IF(C14="","",C14+N(D14)-F14) | H14: =IF(A14="","",YEAR(A14)*100+MONTH(A14))
E15: =IF(C15="","",'3 Sistema'!$C$6) | F15: =IF(C15="","",C15*E15+N(D15)) | G15: =IF(C15="","",C15+N(D15)-F15) | H15: =IF(A15="","",YEAR(A15)*100+MONTH(A15))
E16: =IF(C16="","",'3 Sistema'!$C$6) | F16: =IF(C16="","",C16*E16+N(D16)) | G16: =IF(C16="","",C16+N(D16)-F16) | H16: =IF(A16="","",YEAR(A16)*100+MONTH(A16))
E17: =IF(C17="","",'3 Sistema'!$C$6) | F17: =IF(C17="","",C17*E17+N(D17)) | G17: =IF(C17="","",C17+N(D17)-F17) | H17: =IF(A17="","",YEAR(A17)*100+MONTH(A17))
E18: =IF(C18="","",'3 Sistema'!$C$6) | F18: =IF(C18="","",C18*E18+N(D18)) | G18: =IF(C18="","",C18+N(D18)-F18) | H18: =IF(A18="","",YEAR(A18)*100+MONTH(A18))
E19: =IF(C19="","",'3 Sistema'!$C$6) | F19: =IF(C19="","",C19*E19+N(D19)) | G19: =IF(C19="","",C19+N(D19)-F19) | H19: =IF(A19="","",YEAR(A19)*100+MONTH(A19))
E20: =IF(C20="","",'3 Sistema'!$C$6) | F20: =IF(C20="","",C20*E20+N(D20)) | G20: =IF(C20="","",C20+N(D20)-F20) | H20: =IF(A20="","",YEAR(A20)*100+MONTH(A20))
E21: =IF(C21="","",'3 Sistema'!$C$6) | F21: =IF(C21="","",C21*E21+N(D21)) | G21: =IF(C21="","",C21+N(D21)-F21) | H21: =IF(A21="","",YEAR(A21)*100+MONTH(A21))
E22: =IF(C22="","",'3 Sistema'!$C$6) | F22: =IF(C22="","",C22*E22+N(D22)) | G22: =IF(C22="","",C22+N(D22)-F22) | H22: =IF(A22="","",YEAR(A22)*100+MONTH(A22))
... E304: =IF(C304="","",'3 Sistema'!$C$6) | F304: =IF(C304="","",C304*E304+N(D304)) | G304: =IF(C304="","",C304+N(D304)-F304) | H304: =IF(A304="","",YEAR(A304)*100+MONTH(A304))

Sheet 5 Embalse
A1: 5 · Seguimiento del embalse
A2: El día de pago, anota el saldo del embalse ANTES de pagarte. La hoja sugiere el sueldo, calcula la zona del semáforo y la cascada.
A4: Día de pago | B4: Embalse antes de pagarte | C4: Fase | D4: Sueldo sugerido | E4: Sueldo pagado (si fue distinto) | F4: Embalse después | G4: Sueldos meta | H4: Zona | I4: Excedente sobre la meta | J4: Disfrute (10 %) | K4: Cascada (90 %)
C5: =IF(B5="","",IF(B5>=2*'3 Sistema'!$C$15,"Normal","Arranque")) | D5: =IF(B5="","",IF(B5>=2*'3 Sistema'!$C$15,'3 Sistema'!$C$15,IF(C5="Arranque",MIN('3 Sistema'!$C$22,B5),IF(B5-'3 Sistema'!$C$20>=0.5*'3 Sistema'!$C$15,'3 Sistema'!$C$20,MIN('3 Sistema'!$C$19,B5))))) | F5: =IF(B5="","",B5-IF(E5="",D5,E5)) | G5: =IF(B5="","",IFERROR(F5/'3 Sistema'!$C$15,0)) | H5: =IF(B5="","",IF(G5>=3,"Verde",IF(G5>=1,"Amarillo",IF(G5>=0.5,"Naranja","Rojo")))) | I5: =IF(OR(B5="",N('3 Sistema'!$C$33)=0),"",MAX(0,F5-'3 Sistema'!$C$33)) | J5: =IF(I5="","",I5*0.1) | K5: =IF(I5="","",I5*0.9)
C6: =IF(B6="","",IF(OR(C5="Normal",B6>=2*'3 Sistema'!$C$15),"Normal","Arranque")) | D6: =IF(B6="","",IF(B6>=2*'3 Sistema'!$C$15,'3 Sistema'!$C$15,IF(C6="Arranque",MIN('3 Sistema'!$C$22,B6),IF(B6-'3 Sistema'!$C$20>=0.5*'3 Sistema'!$C$15,'3 Sistema'!$C$20,MIN('3 Sistema'!$C$19,B6))))) | F6: =IF(B6="","",B6-IF(E6="",D6,E6)) | G6: =IF(B6="","",IFERROR(F6/'3 Sistema'!$C$15,0)) | H6: =IF(B6="","",IF(G6>=3,"Verde",IF(G6>=1,"Amarillo",IF(G6>=0.5,"Naranja","Rojo")))) | I6: =IF(OR(B6="",N('3 Sistema'!$C$33)=0),"",MAX(0,F6-'3 Sistema'!$C$33)) | J6: =IF(I6="","",I6*0.1) | K6: =IF(I6="","",I6*0.9)
C7: =IF(B7="","",IF(OR(C6="Normal",B7>=2*'3 Sistema'!$C$15),"Normal","Arranque")) | D7: =IF(B7="","",IF(B7>=2*'3 Sistema'!$C$15,'3 Sistema'!$C$15,IF(C7="Arranque",MIN('3 Sistema'!$C$22,B7),IF(B7-'3 Sistema'!$C$20>=0.5*'3 Sistema'!$C$15,'3 Sistema'!$C$20,MIN('3 Sistema'!$C$19,B7))))) | F7: =IF(B7="","",B7-IF(E7="",D7,E7)) | G7: =IF(B7="","",IFERROR(F7/'3 Sistema'!$C$15,0)) | H7: =IF(B7="","",IF(G7>=3,"Verde",IF(G7>=1,"Amarillo",IF(G7>=0.5,"Naranja","Rojo")))) | I7: =IF(OR(B7="",N('3 Sistema'!$C$33)=0),"",MAX(0,F7-'3 Sistema'!$C$33)) | J7: =IF(I7="","",I7*0.1) | K7: =IF(I7="","",I7*0.9)
C8: =IF(B8="","",IF(OR(C7="Normal",B8>=2*'3 Sistema'!$C$15),"Normal","Arranque")) | D8: =IF(B8="","",IF(B8>=2*'3 Sistema'!$C$15,'3 Sistema'!$C$15,IF(C8="Arranque",MIN('3 Sistema'!$C$22,B8),IF(B8-'3 Sistema'!$C$20>=0.5*'3 Sistema'!$C$15,'3 Sistema'!$C$20,MIN('3 Sistema'!$C$19,B8))))) | F8: =IF(B8="","",B8-IF(E8="",D8,E8)) | G8: =IF(B8="","",IFERROR(F8/'3 Sistema'!$C$15,0)) | H8: =IF(B8="","",IF(G8>=3,"Verde",IF(G8>=1,"Amarillo",IF(G8>=0.5,"Naranja","Rojo")))) | I8: =IF(OR(B8="",N('3 Sistema'!$C$33)=0),"",MAX(0,F8-'3 Sistema'!$C$33)) | J8: =IF(I8="","",I8*0.1) | K8: =IF(I8="","",I8*0.9)
C9: =IF(B9="","",IF(OR(C8="Normal",B9>=2*'3 Sistema'!$C$15),"Normal","Arranque")) | D9: =IF(B9="","",IF(B9>=2*'3 Sistema'!$C$15,'3 Sistema'!$C$15,IF(C9="Arranque",MIN('3 Sistema'!$C$22,B9),IF(B9-'3 Sistema'!$C$20>=0.5*'3 Sistema'!$C$15,'3 Sistema'!$C$20,MIN('3 Sistema'!$C$19,B9))))) | F9: =IF(B9="","",B9-IF(E9="",D9,E9)) | G9: =IF(B9="","",IFERROR(F9/'3 Sistema'!$C$15,0)) | H9: =IF(B9="","",IF(G9>=3,"Verde",IF(G9>=1,"Amarillo",IF(G9>=0.5,"Naranja","Rojo")))) | I9: =IF(OR(B9="",N('3 Sistema'!$C$33)=0),"",MAX(0,F9-'3 Sistema'!$C$33)) | J9: =IF(I9="","",I9*0.1) | K9: =IF(I9="","",I9*0.9)
C10: =IF(B10="","",IF(OR(C9="Normal",B10>=2*'3 Sistema'!$C$15),"Normal","Arranque")) | D10: =IF(B10="","",IF(B10>=2*'3 Sistema'!$C$15,'3 Sistema'!$C$15,IF(C10="Arranque",MIN('3 Sistema'!$C$22,B10),IF(B10-'3 Sistema'!$C$20>=0.5*'3 Sistema'!$C$15,'3 Sistema'!$C$20,MIN('3 Sistema'!$C$19,B10))))) | F10: =IF(B10="","",B10-IF(E10="",D10,E10)) | G10: =IF(B10="","",IFERROR(F10/'3 Sistema'!$C$15,0)) | H10: =IF(B10="","",IF(G10>=3,"Verde",IF(G10>=1,"Amarillo",IF(G10>=0.5,"Naranja","Rojo")))) | I10: =IF(OR(B10="",N('3 Sistema'!$C$33)=0),"",MAX(0,F10-'3 Sistema'!$C$33)) | J10: =IF(I10="","",I10*0.1) | K10: =IF(I10="","",I10*0.9)
C11: =IF(B11="","",IF(OR(C10="Normal",B11>=2*'3 Sistema'!$C$15),"Normal","Arranque")) | D11: =IF(B11="","",IF(B11>=2*'3 Sistema'!$C$15,'3 Sistema'!$C$15,IF(C11="Arranque",MIN('3 Sistema'!$C$22,B11),IF(B11-'3 Sistema'!$C$20>=0.5*'3 Sistema'!$C$15,'3 Sistema'!$C$20,MIN('3 Sistema'!$C$19,B11))))) | F11: =IF(B11="","",B11-IF(E11="",D11,E11)) | G11: =IF(B11="","",IFERROR(F11/'3 Sistema'!$C$15,0)) | H11: =IF(B11="","",IF(G11>=3,"Verde",IF(G11>=1,"Amarillo",IF(G11>=0.5,"Naranja","Rojo")))) | I11: =IF(OR(B11="",N('3 Sistema'!$C$33)=0),"",MAX(0,F11-'3 Sistema'!$C$33)) | J11: =IF(I11="","",I11*0.1) | K11: =IF(I11="","",I11*0.9)
C12: =IF(B12="","",IF(OR(C11="Normal",B12>=2*'3 Sistema'!$C$15),"Normal","Arranque")) | D12: =IF(B12="","",IF(B12>=2*'3 Sistema'!$C$15,'3 Sistema'!$C$15,IF(C12="Arranque",MIN('3 Sistema'!$C$22,B12),IF(B12-'3 Sistema'!$C$20>=0.5*'3 Sistema'!$C$15,'3 Sistema'!$C$20,MIN('3 Sistema'!$C$19,B12))))) | F12: =IF(B12="","",B12-IF(E12="",D12,E12)) | G12: =IF(B12="","",IFERROR(F12/'3 Sistema'!$C$15,0)) | H12: =IF(B12="","",IF(G12>=3,"Verde",IF(G12>=1,"Amarillo",IF(G12>=0.5,"Naranja","Rojo")))) | I12: =IF(OR(B12="",N('3 Sistema'!$C$33)=0),"",MAX(0,F12-'3 Sistema'!$C$33)) | J12: =IF(I12="","",I12*0.1) | K12: =IF(I12="","",I12*0.9)
C13: =IF(B13="","",IF(OR(C12="Normal",B13>=2*'3 Sistema'!$C$15),"Normal","Arranque")) | D13: =IF(B13="","",IF(B13>=2*'3 Sistema'!$C$15,'3 Sistema'!$C$15,IF(C13="Arranque",MIN('3 Sistema'!$C$22,B13),IF(B13-'3 Sistema'!$C$20>=0.5*'3 Sistema'!$C$15,'3 Sistema'!$C$20,MIN('3 Sistema'!$C$19,B13))))) | F13: =IF(B13="","",B13-IF(E13="",D13,E13)) | G13: =IF(B13="","",IFERROR(F13/'3 Sistema'!$C$15,0)) | H13: =IF(B13="","",IF(G13>=3,"Verde",IF(G13>=1,"Amarillo",IF(G13>=0.5,"Naranja","Rojo")))) | I13: =IF(OR(B13="",N('3 Sistema'!$C$33)=0),"",MAX(0,F13-'3 Sistema'!$C$33)) | J13: =IF(I13="","",I13*0.1) | K13: =IF(I13="","",I13*0.9)
C14: =IF(B14="","",IF(OR(C13="Normal",B14>=2*'3 Sistema'!$C$15),"Normal","Arranque")) | D14: =IF(B14="","",IF(B14>=2*'3 Sistema'!$C$15,'3 Sistema'!$C$15,IF(C14="Arranque",MIN('3 Sistema'!$C$22,B14),IF(B14-'3 Sistema'!$C$20>=0.5*'3 Sistema'!$C$15,'3 Sistema'!$C$20,MIN('3 Sistema'!$C$19,B14))))) | F14: =IF(B14="","",B14-IF(E14="",D14,E14)) | G14: =IF(B14="","",IFERROR(F14/'3 Sistema'!$C$15,0)) | H14: =IF(B14="","",IF(G14>=3,"Verde",IF(G14>=1,"Amarillo",IF(G14>=0.5,"Naranja","Rojo")))) | I14: =IF(OR(B14="",N('3 Sistema'!$C$33)=0),"",MAX(0,F14-'3 Sistema'!$C$33)) | J14: =IF(I14="","",I14*0.1) | K14: =IF(I14="","",I14*0.9)
C15: =IF(B15="","",IF(OR(C14="Normal",B15>=2*'3 Sistema'!$C$15),"Normal","Arranque")) | D15: =IF(B15="","",IF(B15>=2*'3 Sistema'!$C$15,'3 Sistema'!$C$15,IF(C15="Arranque",MIN('3 Sistema'!$C$22,B15),IF(B15-'3 Sistema'!$C$20>=0.5*'3 Sistema'!$C$15,'3 Sistema'!$C$20,MIN('3 Sistema'!$C$19,B15))))) | F15: =IF(B15="","",B15-IF(E15="",D15,E15)) | G15: =IF(B15="","",IFERROR(F15/'3 Sistema'!$C$15,0)) | H15: =IF(B15="","",IF(G15>=3,"Verde",IF(G15>=1,"Amarillo",IF(G15>=0.5,"Naranja","Rojo")))) | I15: =IF(OR(B15="",N('3 Sistema'!$C$33)=0),"",MAX(0,F15-'3 Sistema'!$C$33)) | J15: =IF(I15="","",I15*0.1) | K15: =IF(I15="","",I15*0.9)
C16: =IF(B16="","",IF(OR(C15="Normal",B16>=2*'3 Sistema'!$C$15),"Normal","Arranque")) | D16: =IF(B16="","",IF(B16>=2*'3 Sistema'!$C$15,'3 Sistema'!$C$15,IF(C16="Arranque",MIN('3 Sistema'!$C$22,B16),IF(B16-'3 Sistema'!$C$20>=0.5*'3 Sistema'!$C$15,'3 Sistema'!$C$20,MIN('3 Sistema'!$C$19,B16))))) | F16: =IF(B16="","",B16-IF(E16="",D16,E16)) | G16: =IF(B16="","",IFERROR(F16/'3 Sistema'!$C$15,0)) | H16: =IF(B16="","",IF(G16>=3,"Verde",IF(G16>=1,"Amarillo",IF(G16>=0.5,"Naranja","Rojo")))) | I16: =IF(OR(B16="",N('3 Sistema'!$C$33)=0),"",MAX(0,F16-'3 Sistema'!$C$33)) | J16: =IF(I16="","",I16*0.1) | K16: =IF(I16="","",I16*0.9)
C17: =IF(B17="","",IF(OR(C16="Normal",B17>=2*'3 Sistema'!$C$15),"Normal","Arranque")) | D17: =IF(B17="","",IF(B17>=2*'3 Sistema'!$C$15,'3 Sistema'!$C$15,IF(C17="Arranque",MIN('3 Sistema'!$C$22,B17),IF(B17-'3 Sistema'!$C$20>=0.5*'3 Sistema'!$C$15,'3 Sistema'!$C$20,MIN('3 Sistema'!$C$19,B17))))) | F17: =IF(B17="","",B17-IF(E17="",D17,E17)) | G17: =IF(B17="","",IFERROR(F17/'3 Sistema'!$C$15,0)) | H17: =IF(B17="","",IF(G17>=3,"Verde",IF(G17>=1,"Amarillo",IF(G17>=0.5,"Naranja","Rojo")))) | I17: =IF(OR(B17="",N('3 Sistema'!$C$33)=0),"",MAX(0,F17-'3 Sistema'!$C$33)) | J17: =IF(I17="","",I17*0.1) | K17: =IF(I17="","",I17*0.9)
... C40: =IF(B40="","",IF(OR(C39="Normal",B40>=2*'3 Sistema'!$C$15),"Normal","Arranque")) | D40: =IF(B40="","",IF(B40>=2*'3 Sistema'!$C$15,'3 Sistema'!$C$15,IF(C40="Arranque",MIN('3 Sistema'!$C$22,B40),IF(B40-'3 Sistema'!$C$20>=0.5*'3 Sistema'!$C$15,'3 Sistema'!$C$20,MIN('3 Sistema'!$C$19,B40))))) | F40: =IF(B40="","",B40-IF(E40="",D40,E40)) | G40: =IF(B40="","",IFERROR(F40/'3 Sistema'!$C$15,0)) | H40: =IF(B40="","",IF(G40>=3,"Verde",IF(G40>=1,"Amarillo",IF(G40>=0.5,"Naranja","Rojo")))) | I40: =IF(OR(B40="",N('3 Sistema'!$C$33)=0),"",MAX(0,F40-'3 Sistema'!$C$33)) | J40: =IF(I40="","",I40*0.1) | K40: =IF(I40="","",I40*0.9)
A42: Sueldo sugerido: sueldo meta si el embalse tiene al menos 2 sueldos meta antes de pagarte; en fase de arranque, el sueldo de arranque; después del arranque, el sueldo en modo ajuste (zona naranja) o el número de supervivencia (zona roja). Si te pagaste otro monto, anótalo en la columna E.

Sheet 6 Previsiones
A1: 6 · Gastos irregulares y previsiones
A2: Lista los gastos que no son mensuales, con el mes en que llegan (1 = enero … 12 = diciembre).
B4: Total anual de gastos irregulares | C4: =SUM(D11:D40)
B5: Aporte mensual a Previsiones (total ÷ 12) | C5: =C4/12
B6: Capital semilla del primer año | C6: =MAX(0,-MIN(J11:J22))
B7: Mes en que empiezas (1 a 12) | C7: 1
B10: Gasto | C10: Mes (1 a 12) | D10: Monto | F10: Paso | G10: Mes | H10: Aporte | I10: Gastos | J10: Saldo simulado
F11: 1 | G11: =MOD($C$7-1+0,12)+1 | H11: =$C$5 | I11: =SUMIF($C$11:$C$40,G11,$D$11:$D$40) | J11: =H11-I11
F12: 2 | G12: =MOD($C$7-1+1,12)+1 | H12: =$C$5 | I12: =SUMIF($C$11:$C$40,G12,$D$11:$D$40) | J12: =J11+H12-I12
F13: 3 | G13: =MOD($C$7-1+2,12)+1 | H13: =$C$5 | I13: =SUMIF($C$11:$C$40,G13,$D$11:$D$40) | J13: =J12+H13-I13
F14: 4 | G14: =MOD($C$7-1+3,12)+1 | H14: =$C$5 | I14: =SUMIF($C$11:$C$40,G14,$D$11:$D$40) | J14: =J13+H14-I14
F15: 5 | G15: =MOD($C$7-1+4,12)+1 | H15: =$C$5 | I15: =SUMIF($C$11:$C$40,G15,$D$11:$D$40) | J15: =J14+H15-I15
F16: 6 | G16: =MOD($C$7-1+5,12)+1 | H16: =$C$5 | I16: =SUMIF($C$11:$C$40,G16,$D$11:$D$40) | J16: =J15+H16-I16
F17: 7 | G17: =MOD($C$7-1+6,12)+1 | H17: =$C$5 | I17: =SUMIF($C$11:$C$40,G17,$D$11:$D$40) | J17: =J16+H17-I17
F18: 8 | G18: =MOD($C$7-1+7,12)+1 | H18: =$C$5 | I18: =SUMIF($C$11:$C$40,G18,$D$11:$D$40) | J18: =J17+H18-I18
F19: 9 | G19: =MOD($C$7-1+8,12)+1 | H19: =$C$5 | I19: =SUMIF($C$11:$C$40,G19,$D$11:$D$40) | J19: =J18+H19-I19
F20: 10 | G20: =MOD($C$7-1+9,12)+1 | H20: =$C$5 | I20: =SUMIF($C$11:$C$40,G20,$D$11:$D$40) | J20: =J19+H20-I20
F21: 11 | G21: =MOD($C$7-1+10,12)+1 | H21: =$C$5 | I21: =SUMIF($C$11:$C$40,G21,$D$11:$D$40) | J21: =J20+H21-I21
F22: 12 | G22: =MOD($C$7-1+11,12)+1 | H22: =$C$5 | I22: =SUMIF($C$11:$C$40,G22,$D$11:$D$40) | J22: =J21+H22-I22
F24: Si el saldo simulado es negativo en algún mes, el capital semilla es lo que necesitas poner al empezar para que nunca falte.

Sheet 7 Tarifa
A1: 7 · Tu tarifa mínima viable
A2: Capítulo 11. Cuánto necesitas cobrar por hora facturable para sostener todo el sistema.
B4: Sueldo meta × 12 | C4: ='3 Sistema'!C15*12
B5: Gastos de la actividad × 12 | C5: ='3 Sistema'!C8*12
B6: Metas y retiro por año
B7: Ingreso neto anual necesario | C7: =C4+C5+N(C6)
B8: % de reserva de impuestos | C8: ='3 Sistema'!C6
B9: Ingreso bruto anual necesario | C9: =IFERROR(C7/(1-C8),0)
B10: Semanas de vacaciones | C10: 4
B11: Semanas de feriados | C11: 2
B12: Semanas de margen (enfermedad, imprevistos) | C12: 1
B13: Horas de trabajo por semana | C13: 40
B14: % de horas facturables | C14: 0.55
B15: Semanas de trabajo por año | C15: =52-C10-C11-C12
B16: Horas facturables por año | C16: =C15*C13*C14
B17: TARIFA MÍNIMA VIABLE (por hora) | C17: =IFERROR(C9/C16,0)
B18: TARIFA OBJETIVO (× 1,15) | C18: =C17*1.15
B19: Tu tarifa promedio actual (por hora)
B20: Diferencia con la tarifa objetivo | C20: =IF(C19="","",C19-C18)
B22: Para proyectos: horas estimadas × 1,2 (imprevistos) × tarifa objetivo.

Sheet 8 Cartera 90 días
A1: 8 · Cartera de trabajos a 90 días
A2: Lo que esperas cobrar en los próximos tres meses. Confirmado = 100 %, Probable = 70 %, Posible = 30 % (convención práctica).
A4: Cliente / trabajo | B4: Monto bruto | C4: Mes (1, 2 o 3) | D4: Estado | E4: Probabilidad | F4: Ponderado | H4: Resumen por mes | I4: Mes 1 | J4: Mes 2 | K4: Mes 3
E5: =IF(D5="","",IF(D5="Confirmado",1,IF(D5="Probable",0.7,0.3))) | F5: =IF(OR(B5="",E5=""),"",B5*E5) | H5: Bruto ponderado | I5: =SUMIF($C$5:$C$34,1,$F$5:$F$34) | J5: =SUMIF($C$5:$C$34,2,$F$5:$F$34) | K5: =SUMIF($C$5:$C$34,3,$F$5:$F$34)
E6: =IF(D6="","",IF(D6="Confirmado",1,IF(D6="Probable",0.7,0.3))) | F6: =IF(OR(B6="",E6=""),"",B6*E6) | H6: − Reserva de impuestos | I6: =-I5*'3 Sistema'!$C$6 | J6: =-J5*'3 Sistema'!$C$6 | K6: =-K5*'3 Sistema'!$C$6
E7: =IF(D7="","",IF(D7="Confirmado",1,IF(D7="Probable",0.7,0.3))) | F7: =IF(OR(B7="",E7=""),"",B7*E7) | H7: − Gastos de la actividad | I7: =-'3 Sistema'!$C$8 | J7: =-'3 Sistema'!$C$8 | K7: =-'3 Sistema'!$C$8
E8: =IF(D8="","",IF(D8="Confirmado",1,IF(D8="Probable",0.7,0.3))) | F8: =IF(OR(B8="",E8=""),"",B8*E8) | H8: Disponible esperado | I8: =SUM(I5:I7) | J8: =SUM(J5:J7) | K8: =SUM(K5:K7)
E9: =IF(D9="","",IF(D9="Confirmado",1,IF(D9="Probable",0.7,0.3))) | F9: =IF(OR(B9="",E9=""),"",B9*E9) | H9: Sueldo meta | I9: ='3 Sistema'!$C$15 | J9: ='3 Sistema'!$C$15 | K9: ='3 Sistema'!$C$15
E10: =IF(D10="","",IF(D10="Confirmado",1,IF(D10="Probable",0.7,0.3))) | F10: =IF(OR(B10="",E10=""),"",B10*E10) | H10: Diferencia | I10: =I8-I9 | J10: =J8-J9 | K10: =K8-K9
E11: =IF(D11="","",IF(D11="Confirmado",1,IF(D11="Probable",0.7,0.3))) | F11: =IF(OR(B11="",E11=""),"",B11*E11) | H11: Señal | I11: =IF(I9=0,"",IF(I10<0,"Mes flojo: trabajar","OK")) | J11: =IF(J9=0,"",IF(J10<0,"Mes flojo: trabajar","OK")) | K11: =IF(K9=0,"",IF(K10<0,"Mes flojo: trabajar","OK"))
E12: =IF(D12="","",IF(D12="Confirmado",1,IF(D12="Probable",0.7,0.3))) | F12: =IF(OR(B12="",E12=""),"",B12*E12)
E13: =IF(D13="","",IF(D13="Confirmado",1,IF(D13="Probable",0.7,0.3))) | F13: =IF(OR(B13="",E13=""),"",B13*E13)
E14: =IF(D14="","",IF(D14="Confirmado",1,IF(D14="Probable",0.7,0.3))) | F14: =IF(OR(B14="",E14=""),"",B14*E14)
E15: =IF(D15="","",IF(D15="Confirmado",1,IF(D15="Probable",0.7,0.3))) | F15: =IF(OR(B15="",E15=""),"",B15*E15)
E16: =IF(D16="","",IF(D16="Confirmado",1,IF(D16="Probable",0.7,0.3))) | F16: =IF(OR(B16="",E16=""),"",B16*E16)
E17: =IF(D17="","",IF(D17="Confirmado",1,IF(D17="Probable",0.7,0.3))) | F17: =IF(OR(B17="",E17=""),"",B17*E17)
E18: =IF(D18="","",IF(D18="Confirmado",1,IF(D18="Probable",0.7,0.3))) | F18: =IF(OR(B18="",E18=""),"",B18*E18)
E19: =IF(D19="","",IF(D19="Confirmado",1,IF(D19="Probable",0.7,0.3))) | F19: =IF(OR(B19="",E19=""),"",B19*E19)
E20: =IF(D20="","",IF(D20="Confirmado",1,IF(D20="Probable",0.7,0.3))) | F20: =IF(OR(B20="",E20=""),"",B20*E20)
E21: =IF(D21="","",IF(D21="Confirmado",1,IF(D21="Probable",0.7,0.3))) | F21: =IF(OR(B21="",E21=""),"",B21*E21)
E22: =IF(D22="","",IF(D22="Confirmado",1,IF(D22="Probable",0.7,0.3))) | F22: =IF(OR(B22="",E22=""),"",B22*E22)
E23: =IF(D23="","",IF(D23="Confirmado",1,IF(D23="Probable",0.7,0.3))) | F23: =IF(OR(B23="",E23=""),"",B23*E23)
... E34: =IF(D34="","",IF(D34="Confirmado",1,IF(D34="Probable",0.7,0.3))) | F34: =IF(OR(B34="",E34=""),"",B34*E34)
